gmail_oauth_backend/__init__.py
gmail_oauth_backend/admin.py
gmail_oauth_backend/apps.py
gmail_oauth_backend/models.py
gmail_oauth_backend/management/__init__.py
gmail_oauth_backend/management/commands/__init__.py
gmail_oauth_backend/management/commands/init_gmail_oauth_token.py
gmail_oauth_backend/migrations/0001_initial.py
gmail_oauth_backend/migrations/0002_alter_refreshtoken_value.py
gmail_oauth_backend/migrations/__init__.py
django_gmail_oauth_backend-0.2.0.dist-info/LICENSE
django_gmail_oauth_backend-0.2.0.dist-info/METADATA
django_gmail_oauth_backend-0.2.0.dist-info/WHEEL
django_gmail_oauth_backend-0.2.0.dist-info/top_level.txt
django_gmail_oauth_backend-0.2.0.dist-info/RECORD
