Metadata-Version: 2.1
Name: django-gmail-oauth-backend
Version: 0.2.0
Summary: Simplifies Gmail authentication for Django applications using OAuth 2.0. WITHOUT App Passwords!
Home-page: https://github.com/yeongbin-jo/django-gmail-oauth-backend
Author: Yeongbin Jo
Author-email: iam.yeongbin.jo@gmail.com
License: MIT
Classifier: Development Status :: 4 - Beta
Classifier: Framework :: Django
Classifier: Framework :: Django :: 5.0
Classifier: Framework :: Django :: 5.1
Classifier: Programming Language :: Python :: 3
Classifier: License :: OSI Approved :: MIT License
Classifier: Operating System :: OS Independent
Requires-Python: >=3.11
License-File: LICENSE
Requires-Dist: Django>=5.0
Requires-Dist: google-auth>=2.0
Requires-Dist: google-api-python-client>=2.0
Requires-Dist: google-auth-oauthlib>=1.2
